easygraphics/__init__.py
easygraphics/consts.py
easygraphics/easygraphics.py
easygraphics/graphwin.py
easygraphics/image.py
easygraphics/utils3d.py
easygraphics/_utils/__init__.py
easygraphics/_utils/invoke_in_app_thread.py
easygraphics/dialog/__init__.py
easygraphics/dialog/_indexed_order_list.py
easygraphics/dialog/calendardialog.py
easygraphics/dialog/dialog.py
easygraphics/dialog/imagedialog.py
easygraphics/dialog/multichoice.py
easygraphics/dialog/multifields.py
easygraphics/dialog/tableview.py
easygraphics/dialog/textdialog.py
easygraphics/legacy/__init__.py
easygraphics/legacy/legacy.py
easygraphics/music/__init__.py
easygraphics/music/music.py
easygraphics/processing/__init__.py
easygraphics/processing/processing.py
easygraphics/processing/processingwidget.py
easygraphics/turtle/__init__.py
easygraphics/turtle/turleclass.py
easygraphics/turtle/turtle.png
easygraphics/turtle/turtle.py
easygraphics/widget/__init__.py
easygraphics/widget/imagewidget.py
easygraphics/widget/turtlewidget.py
easygraphics-2.0.1.2.dist-info/AUTHORS.rst
easygraphics-2.0.1.2.dist-info/LICENSE
easygraphics-2.0.1.2.dist-info/METADATA
easygraphics-2.0.1.2.dist-info/WHEEL
easygraphics-2.0.1.2.dist-info/top_level.txt
easygraphics-2.0.1.2.dist-info/RECORD
