Metadata-Version: 2.1
Name: easygraphics
Version: 2.0.1.2
Summary: "A TC Graphics style like Graphics Library"
Home-page: https://github.com/royqh1979/PyEasyGraphics
Author: Roy Qu
Author-email: royqh1979@gmail.com
License: BSD
Keywords: easygraphics,computer graphics,Turbo C graphics,Borland Graphics Interface
Platform: UNKNOWN
Classifier: Development Status :: 5 - Production/Stable
Classifier: License :: OSI Approved :: BSD License
Classifier: Intended Audience :: Education
Classifier: Topic :: Multimedia :: Graphics
Classifier: Programming Language :: Python :: 3
Classifier: Programming Language :: Python :: 3.5
Classifier: Programming Language :: Python :: 3.6
Classifier: Programming Language :: Python :: 3.7
Classifier: Programming Language :: Python :: 3.8
Requires-Dist: PyQt5
Requires-Dist: pygame
Requires-Dist: apng
